<?xml version="1.0" encoding="utf-8"?>

<odoo>
<data>

    <record model="ir.ui.view" id="view_product_template_extra_prices">
        <field name="name">product.product.extra.prices</field>
        <field name="model">product.product</field> 
        <field name="inherit_id" ref="product.product_normal_form_view"/>
        <field name="arch" type="xml">

            <xpath expr="sheet/notebook/page[@name='general_information']" position="inside">
                <group string="Precios Extras">
                    <field colspan="2" name="precios_extras_ids" nolabel="1" context="{'default_product_id': active_id}" />
                </group>
            </xpath>
            


        </field>
    </record> 
    
    
    
    
    
    
    
    
    
    


    
</data>
</odoo>